README.md
setup.cfg
setup.py
coinuma_sdk/__init__.py
coinuma_sdk.egg-info/PKG-INFO
coinuma_sdk.egg-info/SOURCES.txt
coinuma_sdk.egg-info/dependency_links.txt
coinuma_sdk.egg-info/requires.txt
coinuma_sdk.egg-info/top_level.txt
coinuma_sdk/api/__init__.py
coinuma_sdk/api/client.py
coinuma_sdk/api/private.py
coinuma_sdk/api/public.py
coinuma_sdk/const/__init__.py
coinuma_sdk/const/endpoints_private.py
coinuma_sdk/const/endpoints_public.py
coinuma_sdk/const/url_addresses.py
coinuma_sdk/errors/__init__.py
coinuma_sdk/errors/connection.py
coinuma_sdk/model/__init__.py
coinuma_sdk/model/asset.py
coinuma_sdk/model/balance.py
coinuma_sdk/model/commissions.py
coinuma_sdk/model/limits.py
coinuma_sdk/model/model.py
coinuma_sdk/model/order.py
coinuma_sdk/model/orderbook.py
coinuma_sdk/model/orderbook_row.py
coinuma_sdk/model/summary.py
coinuma_sdk/model/symbol.py
coinuma_sdk/model/ticker.py
coinuma_sdk/model/trade.py